turbovault4dbt/main.py
turbovault4dbt/backend/bigquery.py
turbovault4dbt/backend/csv.py
turbovault4dbt/backend/db.py
turbovault4dbt/backend/excel.py
turbovault4dbt/backend/googleSheets.py
turbovault4dbt/backend/graph_utils.py
turbovault4dbt/backend/snowflake.py
turbovault4dbt/backend/sources.py
turbovault4dbt/backend/turbovault.py
turbovault4dbt/backend/config/config.ini
turbovault4dbt/backend/config/config.py
turbovault4dbt/backend/procs/sqlite3/generate_erd.py
turbovault4dbt/backend/procs/sqlite3/generate_selected_entities.py
turbovault4dbt/backend/procs/sqlite3/hub.py
turbovault4dbt/backend/procs/sqlite3/link.py
turbovault4dbt/backend/procs/sqlite3/ma_satellite.py
turbovault4dbt/backend/procs/sqlite3/nh_link.py
turbovault4dbt/backend/procs/sqlite3/nh_satellite.py
turbovault4dbt/backend/procs/sqlite3/pit.py
turbovault4dbt/backend/procs/sqlite3/properties.py
turbovault4dbt/backend/procs/sqlite3/ref.py
turbovault4dbt/backend/procs/sqlite3/rt_satellite.py
turbovault4dbt/backend/procs/sqlite3/satellite.py
turbovault4dbt/backend/procs/sqlite3/sources.py
turbovault4dbt/backend/procs/sqlite3/stage.py
turbovault4dbt/backend/procs/sqlite3/utils.py
turbovault4dbt/backend/templates/control_snap_v0.txt
turbovault4dbt/backend/templates/control_snap_v1.txt
turbovault4dbt/backend/templates/hub.txt
turbovault4dbt/backend/templates/hub_test.txt
turbovault4dbt/backend/templates/link.txt
turbovault4dbt/backend/templates/link_hub_test.txt
turbovault4dbt/backend/templates/link_test.txt
turbovault4dbt/backend/templates/ma_sat_v0.txt
turbovault4dbt/backend/templates/ma_sat_v1.txt
turbovault4dbt/backend/templates/nh_link.txt
turbovault4dbt/backend/templates/nh_sat.txt
turbovault4dbt/backend/templates/pit_test.txt
turbovault4dbt/backend/templates/pit_v1.txt
turbovault4dbt/backend/templates/record_tracking_sat.txt
turbovault4dbt/backend/templates/ref_hub.txt
turbovault4dbt/backend/templates/ref_sat_v0.txt
turbovault4dbt/backend/templates/ref_sat_v1.txt
turbovault4dbt-0.2.7.dist-info/licenses/LICENSE
turbovault4dbt-0.2.7.dist-info/METADATA
turbovault4dbt-0.2.7.dist-info/WHEEL
turbovault4dbt-0.2.7.dist-info/entry_points.txt
turbovault4dbt-0.2.7.dist-info/top_level.txt
turbovault4dbt-0.2.7.dist-info/RECORD
