Metadata-Version: 2.4
Name: turbovault4dbt
Version: 0.2.7
Summary: CLI for Turbovault 4 DBT
Author-email: Pawel <pawel.sala01@wp.pl>
License:                                  Apache License
Requires-Python: >=3.8
License-File: LICENSE
Requires-Dist: asn1crypto
Requires-Dist: cachetools
Requires-Dist: matplotlib
Requires-Dist: certifi
Requires-Dist: cffi
Requires-Dist: charset-normalizer
Requires-Dist: cryptography
Requires-Dist: db-dtypes
Requires-Dist: et_xmlfile
Requires-Dist: filelock
Requires-Dist: google-api-core
Requires-Dist: google-auth
Requires-Dist: google-auth-oauthlib
Requires-Dist: google-cloud-bigquery
Requires-Dist: google-cloud-core
Requires-Dist: google-crc32c
Requires-Dist: google-resumable-media
Requires-Dist: googleapis-common-protos
Requires-Dist: grpcio
Requires-Dist: grpcio-status
Requires-Dist: gspread
Requires-Dist: idna
Requires-Dist: numpy
Requires-Dist: oauthlib
Requires-Dist: openpyxl
Requires-Dist: packaging
Requires-Dist: pandas
Requires-Dist: platformdirs
Requires-Dist: proto-plus
Requires-Dist: protobuf
Requires-Dist: pyarrow
Requires-Dist: pyasn1
Requires-Dist: pyasn1_modules
Requires-Dist: pycparser
Requires-Dist: PyJWT
Requires-Dist: pyOpenSSL
Requires-Dist: python-dateutil
Requires-Dist: pytz
Requires-Dist: requests
Requires-Dist: requests-oauthlib
Requires-Dist: rsa
Requires-Dist: six
Requires-Dist: snowflake-connector-python
Requires-Dist: sortedcontainers
Requires-Dist: tomlkit
Requires-Dist: typing_extensions
Requires-Dist: tzdata
Requires-Dist: urllib3
Requires-Dist: networkx
Dynamic: license-file
